{
    "prepared": "2023-12-03 06:20:02",
    "id": "2.10.56.8",
    "agency_id": "36",
    "codes": {
        "IR": {
            "name": "ССРД - Международные резервные активы",
            "values": [
                [
                    "1",
                    "Всего"
                ],
                [
                    "2",
                    "Резервные активы в иностранной валюте"
                ],
                [
                    "3",
                    "Резервная позиция в МВФ"
                ],
                [
                    "4",
                    "СДР"
                ],
                [
                    "5",
                    "Золото"
                ],
                [
                    "6",
                    "Другие резервные активы"
                ]
            ]
        }
    },
    "full_name": "Международные резервные активы",
    "unit": "миллион долларов США",
    "periodicity": {
        "value": "По специальному графику - за отчетный месяц",
        "releases": "по специальному графику",
        "next": "2024-10-07 21:00:00"
    },
    "data_range": [
        2019,
        2021
    ],
    "updated": "2021-10-08 09:05:50",
    "methodology": "см. методологические материалы Банка России по статистике внешнего сектора, в частности \"Методологический комментарий к международным резервам Российской Федерации\"",
    "agency_name": "Министерство финансов Российской Федерации",
    "agency_dept": "Департамент бюджетной политики и стратегического планирования",
    "classifier": {
        "id": "2.10.56.",
        "path": "По федеральному плану статработ / Росстат и другие субъекты официального статистического учета / Официальная статистическая информация, предоставляемая в соответствии с вопросниками международных организаций / Информация, публикуемая в соответствии со Специальным стандартом распространения данных Международного валютного фонда (ССРД МВФ)"
    },
    "prepared_by": {
        "name": "Авакян С.А.; Лутохин М.О.",
        "contacts": "8 (495) 983-38-83 (1542) (1546) Samvel.Avakian@minfin.gov.ru Mikhail.Lutokhin@minfin.gov.ru"
    },
    "data": [
        [
            "ССРД - Международные резервные активы",
            "Всего",
            "миллион долларов США",
            "январь",
            2020,
            562306.4
        ],
        [
            "ССРД - Международные резервные активы",
            "Всего",
            "миллион долларов США",
            "февраль",
            2020,
            570380.8
        ],
        [
            "ССРД - Международные резервные активы",
            "Всего",
            "миллион долларов США",
            "март",
            2020,
            563473.4
        ],
        [
            "ССРД - Международные резервные активы",
            "Всего",
            "миллион долларов США",
            "апрель",
            2020,
            566011.5
        ],
        [
            "ССРД - Международные резервные активы",
            "Всего",
            "миллион долларов США",
            "май",
            2020,
            566133.9
        ],
        [
            "ССРД - Международные резервные активы",
            "Всего",
            "миллион долларов США",
            "июнь",
            2020,
            568872.3
        ],
        [
            "ССРД - Международные резервные активы",
            "Всего",
            "миллион долларов США",
            "июль",
            2020,
            591753.0
        ],
        [
            "ССРД - Международные резервные активы",
            "Всего",
            "миллион долларов США",
            "август",
            2020,
            594422.0
        ],
        [
            "ССРД - Международные резервные активы",
            "Всего",
            "миллион долларов США",
            "сентябрь",
            2020,
            583426.0
        ],
        [
            "ССРД - Международные резервные активы",
            "Всего",
            "миллион долларов США",
            "октябрь",
            2020,
            582845.0
        ],
        [
            "ССРД - Международные резервные активы",
            "Всего",
            "миллион долларов США",
            "ноябрь",
            2020,
            582676.0
        ],
        [
            "ССРД - Международные резервные активы",
            "Всего",
            "миллион долларов США",
            "декабрь",
            2020,
            595774.0
        ],
        [
            "ССРД - Международные резервные активы",
            "Всего",
            "миллион долларов США",
            "январь",
            2021,
            590685.0
        ],
        [
            "ССРД - Международные резервные активы",
            "Всего",
            "миллион долларов США",
            "февраль",
            2021,
            586266.0
        ],
        [
            "ССРД - Международные резервные активы",
            "Всего",
            "миллион долларов США",
            "март",
            2021,
            573322.0
        ],
        [
            "ССРД - Международные резервные активы",
            "Всего",
            "миллион долларов США",
            "апрель",
            2021,
            590476.0
        ],
        [
            "ССРД - Международные резервные активы",
            "Всего",
            "миллион долларов США",
            "май",
            2021,
            605232.0
        ],
        [
            "ССРД - Международные резервные активы",
            "Всего",
            "миллион долларов США",
            "июнь",
            2021,
            591529.0
        ],
        [
            "ССРД - Международные резервные активы",
            "Всего",
            "миллион долларов США",
            "июль",
            2021,
            601003.0
        ],
        [
            "ССРД - Международные резервные активы",
            "Всего",
            "миллион долларов США",
            "август",
            2021,
            618181.0
        ]
    ]
}